TASMANIAN_DEVIL/TASMANIAN_DEVIL.py
TASMANIAN_DEVIL/__init__.py
TASMANIAN_DEVIL/_version.py
TASMANIAN_DEVIL/flux.py
TASMANIAN_DEVIL/gene.py
TASMANIAN_DEVIL/model.py
TASMANIAN_DEVIL/visualization.py
TASMANIAN_DEVIL-0.1.0.dist-info/DESCRIPTION.rst
TASMANIAN_DEVIL-0.1.0.dist-info/METADATA
TASMANIAN_DEVIL-0.1.0.dist-info/RECORD
TASMANIAN_DEVIL-0.1.0.dist-info/WHEEL
TASMANIAN_DEVIL-0.1.0.dist-info/entry_points.txt
TASMANIAN_DEVIL-0.1.0.dist-info/metadata.json
TASMANIAN_DEVIL-0.1.0.dist-info/top_level.txt
