Metadata-Version: 2.0
Name: TASMANIAN-DEVIL
Version: 0.1.0
Summary: TASMANIAN DEVIL: a software package for classifying gene activity from omics data sets, simplifying metabolic networks, and visualizing the estimated phenotypic fluxes of nutrients
Home-page: https://tlawrence3.github.io/Tasmanian-Devil
Author: Edwin H. Gibb and Travis J. Lawrence
Author-email: UNKNOWN
License: LGPLv3
Platform: UNKNOWN
Classifier: Development Status :: 4 - Beta
Classifier: Environment :: Console
Classifier: Intended Audience :: Science/Research
Classifier: License :: OSI Approved :: GNU Lesser General Public License v3 (LGPLv3)
Classifier: Natural Language :: English
Classifier: Operating System :: MacOS :: MacOS X
Classifier: Operating System :: POSIX :: Linux
Classifier: Programming Language :: Python :: 2.7
Classifier: Programming Language :: Python :: 3.6
Classifier: Topic :: Scientific/Engineering :: Bio-Informatics
Requires-Dist: numpy
Requires-Dist: scipy (<1.0)
Requires-Dist: pandas
Requires-Dist: pycrypto
Requires-Dist: argparse
Requires-Dist: cobra (==0.8.2)
Requires-Dist: sympy
Requires-Dist: python-libsbml
